muagent/__init__.py
muagent/ekg_project.py
muagent/project_manager.py
muagent/agents/__init__.py
muagent/agents/agent_util.py
muagent/agents/base_agent.py
muagent/agents/functioncall_agent.py
muagent/agents/group_agent.py
muagent/agents/react_agent.py
muagent/agents/single_agent.py
muagent/agents/task_agent.py
muagent/agents/user_agent.py
muagent/agents/util.py
muagent/base_configs/__init__.py
muagent/base_configs/env_config.py
muagent/base_configs/prompts/__init__.py
muagent/base_configs/prompts/agent_selector_template_prompt.py
muagent/base_configs/prompts/checker_template_prompt.py
muagent/base_configs/prompts/code2doc_template_prompt.py
muagent/base_configs/prompts/code2test_template_prompt.py
muagent/base_configs/prompts/executor_template_prompt.py
muagent/base_configs/prompts/functioncall_template_prompt.py
muagent/base_configs/prompts/input_template_prompt.py
muagent/base_configs/prompts/intention_template_prompt.py
muagent/base_configs/prompts/metagpt_prompt.py
muagent/base_configs/prompts/planner_template_prompt.py
muagent/base_configs/prompts/qa_template_prompt.py
muagent/base_configs/prompts/react_code_prompt.py
muagent/base_configs/prompts/react_template_prompt.py
muagent/base_configs/prompts/react_tool_code_planner_prompt.py
muagent/base_configs/prompts/react_tool_code_prompt.py
muagent/base_configs/prompts/react_tool_prompt.py
muagent/base_configs/prompts/refine_template_prompt.py
muagent/base_configs/prompts/simple_prompts.py
muagent/base_configs/prompts/summary_template_prompt.py
muagent/chat/__init__.py
muagent/chat/agent_chat.py
muagent/chat/base_chat.py
muagent/chat/code_chat.py
muagent/chat/knowledge_chat.py
muagent/chat/llm_chat.py
muagent/chat/search_chat.py
muagent/chat/utils.py
muagent/codechat/__init__.py
muagent/codechat/code_analyzer/__init__.py
muagent/codechat/code_analyzer/code_analyzer.py
muagent/codechat/code_analyzer/code_dedup.py
muagent/codechat/code_analyzer/code_intepreter.py
muagent/codechat/code_analyzer/code_preprocess.py
codefuse_muagent-0.1.1.dist-info/LICENSE.md
codefuse_muagent-0.1.1.dist-info/METADATA
codefuse_muagent-0.1.1.dist-info/WHEEL
codefuse_muagent-0.1.1.dist-info/top_level.txt
codefuse_muagent-0.1.1.dist-info/RECORD
